jsoup/__init__.py
jsoup-0.0.1.dist-info/LICENSE
jsoup-0.0.1.dist-info/METADATA
jsoup-0.0.1.dist-info/WHEEL
jsoup-0.0.1.dist-info/top_level.txt
jsoup-0.0.1.dist-info/RECORD
