Metadata-Version: 2.1
Name: jsoup
Version: 0.0.1
Summary: Convert JSON to BeautifulSoup object
Home-page: https://github.com/MrDebugger/jsoup
Author: Ijaz Ur Rahim
Author-email: ijazkhan095@gmail.com
License: MIT
Keywords: parser,html,bs4,BeautifulSoup,soup,jsoup,json,builder
Platform: UNKNOWN
Classifier: License :: OSI Approved :: MIT License
Classifier: Programming Language :: Python :: 3
Requires-Python: >=3.6
Requires-Dist: beautifulsoup4 (==4.9.3)
